pynanopoolapi/__init__.py
pynanopoolapi-0.1.dist-info/DESCRIPTION.rst
pynanopoolapi-0.1.dist-info/METADATA
pynanopoolapi-0.1.dist-info/RECORD
pynanopoolapi-0.1.dist-info/WHEEL
pynanopoolapi-0.1.dist-info/metadata.json
pynanopoolapi-0.1.dist-info/top_level.txt
