Metadata-Version: 2.0
Name: pynanopoolapi
Version: 0.1
Summary: Simple Python API Wrapper for Nanopool
Home-page: http://github.com/concongo/pynanopoolapi
Author: J. Fernando Gonzalez
Author-email: jfgonzalem@gmail.com
License: MIT
Keywords: API Nanopool
Platform: UNKNOWN
Requires-Python: >=2.6,<3
